img2pdf.py
jp2.py
img2pdf-0.4.1.dist-info/LICENSE
img2pdf-0.4.1.dist-info/METADATA
img2pdf-0.4.1.dist-info/WHEEL
img2pdf-0.4.1.dist-info/entry_points.txt
img2pdf-0.4.1.dist-info/pbr.json
img2pdf-0.4.1.dist-info/top_level.txt
img2pdf-0.4.1.dist-info/zip-safe
img2pdf-0.4.1.dist-info/RECORD
