Metadata-Version: 2.1
Name: img2pdf
Version: 0.4.1
Summary: Convert images to PDF via direct JPEG inclusion.
Home-page: https://gitlab.mister-muffin.de/josch/img2pdf
Author: Johannes 'josch' Schauer
Author-email: josch@mister-muffin.de
License: LGPL
Download-URL: https://gitlab.mister-muffin.de/josch/img2pdf/repository/archive.tar.gz?ref=0.4.1
Keywords: jpeg pdf converter
Platform: UNKNOWN
Classifier: Development Status :: 5 - Production/Stable
Classifier: Intended Audience :: Developers
Classifier: Intended Audience :: Other Audience
Classifier: Environment :: Console
Classifier: Programming Language :: Python
Classifier: Programming Language :: Python :: 3
Classifier: Programming Language :: Python :: 3.5
Classifier: Programming Language :: Python :: Implementation :: CPython
Classifier: Programming Language :: Python :: Implementation :: PyPy
Classifier: License :: OSI Approved :: GNU Lesser General Public License v3 (LGPLv3)
Classifier: Natural Language :: English
Classifier: Operating System :: OS Independent
Provides-Extra: gui
